server/__init__.py
server/chat.py
server/log/server.log
server/log/server.log.2023-04-25
server/log/server.log.2023-05-02
server/log/server.log.2023-05-16
server/log/server.log.2023-05-23
server/log/server.log.2023-05-30
server/log/server_log_config.py
server/server.py
server/server_db.py
server/sqlite-1.db
server/sqlite.db
gb_chat_server_alexey_01-0.1.0.dist-info/WHEEL
gb_chat_server_alexey_01-0.1.0.dist-info/METADATA
gb_chat_server_alexey_01-0.1.0.dist-info/RECORD
