Metadata-Version: 2.1
Name: gb-chat-server-alexey-01
Version: 0.1.0
Summary: 
Author: Alexey Ryzhkov
Author-email: aler32@mail.ru
Requires-Python: >=3.10,<4.0
Classifier: Programming Language :: Python :: 3
Classifier: Programming Language :: Python :: 3.10
Classifier: Programming Language :: Python :: 3.11
Requires-Dist: chardet (>=5.1.0,<6.0.0)
Requires-Dist: cx-freeze (>=6.15.1,<7.0.0)
Requires-Dist: pyqt5 (>=5.15.9,<6.0.0)
Requires-Dist: pyqt5-tools (>=5.15.9.3.3,<6.0.0.0.0)
Requires-Dist: pyyaml (>=6.0,<7.0)
Requires-Dist: sphinx (>=7.0.1,<8.0.0)
Requires-Dist: sqlalchemy (==1.4.46)
Requires-Dist: tabulate (>=0.9.0,<0.10.0)
